thumbsup/__init__.py
thumbsup/main.py
thumbsup-0.9.dist-info/LICENSE
thumbsup-0.9.dist-info/METADATA
thumbsup-0.9.dist-info/WHEEL
thumbsup-0.9.dist-info/entry_points.txt
thumbsup-0.9.dist-info/top_level.txt
thumbsup-0.9.dist-info/RECORD
