Metadata-Version: 2.1
Name: thumbsup
Version: 0.9
Summary: A CLI tool for generating thumbnails from video files.
Home-page: https://github.com/ethanforvest/thumbsup
Author: Ethan Forvest
Author-email: your.email@example.com
Classifier: Programming Language :: Python :: 3
Classifier: License :: OSI Approved :: MIT License
Classifier: Operating System :: OS Independent
Requires-Python: >=3.11
License-File: LICENSE
Requires-Dist: opencv-python
